matplotlib_map_utils/__init__.py
matplotlib_map_utils/core/__init__.py
matplotlib_map_utils/core/inset_map.py
matplotlib_map_utils/core/north_arrow.py
matplotlib_map_utils/core/scale_bar.py
matplotlib_map_utils/defaults/__init__.py
matplotlib_map_utils/defaults/inset_map.py
matplotlib_map_utils/defaults/north_arrow.py
matplotlib_map_utils/defaults/scale_bar.py
matplotlib_map_utils/scratch/map_utils.py
matplotlib_map_utils/scratch/north_arrow_old_classes.py
matplotlib_map_utils/utils/__init__.py
matplotlib_map_utils/utils/usa.json
matplotlib_map_utils/utils/usa.py
matplotlib_map_utils/validation/__init__.py
matplotlib_map_utils/validation/functions.py
matplotlib_map_utils/validation/inset_map.py
matplotlib_map_utils/validation/north_arrow.py
matplotlib_map_utils/validation/scale_bar.py
matplotlib_map_utils-3.1.1.dist-info/licenses/LICENSE
matplotlib_map_utils-3.1.1.dist-info/METADATA
matplotlib_map_utils-3.1.1.dist-info/WHEEL
matplotlib_map_utils-3.1.1.dist-info/top_level.txt
matplotlib_map_utils-3.1.1.dist-info/RECORD
