Metadata-Version: 2.4
Name: matplotlib-map-utils
Version: 3.1.1
Summary: A suite of tools for creating maps in matplotlib
Author-email: David Moss <davidmoss1221@gmail.com>
License: GNU GENERAL PUBLIC LICENSE
Project-URL: Homepage, https://github.com/moss-xyz/matplotlib-map-utils/
Project-URL: Bug Tracker, https://github.com/moss-xyz/matplotlib-map-utils/issues
Classifier: Programming Language :: Python :: 3
Classifier: License :: OSI Approved :: GNU General Public License (GPL)
Classifier: Operating System :: OS Independent
Classifier: Framework :: Matplotlib
Requires-Python: >=3.10
License-File: LICENSE
Requires-Dist: matplotlib>=3.9.0
Requires-Dist: cartopy>=0.23.0
Requires-Dist: great-circle-calculator>=1.3.1
Dynamic: license-file
